qyweixin/__init__.py
qyweixin/get_token.py
qyweixin/push_message.py
qyweixin/upload.py
qyweixin-0.3.1.dist-info/DESCRIPTION.rst
qyweixin-0.3.1.dist-info/METADATA
qyweixin-0.3.1.dist-info/RECORD
qyweixin-0.3.1.dist-info/WHEEL
qyweixin-0.3.1.dist-info/metadata.json
qyweixin-0.3.1.dist-info/top_level.txt
