Metadata-Version: 2.0
Name: qyweixin
Version: 0.3.1
Summary: Interface for Tencent enterprise weixin.
Home-page: https://github.com/MoeLove/qyweixin
Author: TaoBeier
Author-email: zhangjintao9020@gmail.com
License: MIT
Platform: any
Classifier: Development Status :: 4 - Beta
Classifier: Intended Audience :: Developers
Classifier: Natural Language :: English
Classifier: License :: OSI Approved :: MIT License
Classifier: Programming Language :: Python
Classifier: Programming Language :: Python :: 2.7
Classifier: Topic :: Software Development :: Libraries
Classifier: Topic :: Software Development :: Libraries :: Python Modules
